hegel/__init__.py
hegel/scribe.py
hegel/utils.py
hegel/version.py
hegel-0.0.3.dist-info/LICENSE
hegel-0.0.3.dist-info/METADATA
hegel-0.0.3.dist-info/WHEEL
hegel-0.0.3.dist-info/top_level.txt
hegel-0.0.3.dist-info/RECORD
