Metadata-Version: 2.1
Name: hegel
Version: 0.0.3
Summary: Supercharge your LLM with a frictionless wrapper
Home-page: https://github.com/hegelai/hegel
Author: Hegel AI
Author-email: Hegel AI <team@hegel-ai.com>
License: Proprietary
Project-URL: Homepage, https://github.com/hegelai/hegel
Project-URL: Bug Tracker, https://github.com/hegelai/hegel
Classifier: Programming Language :: Python :: 3
Classifier: License :: Other/Proprietary License
Classifier: Operating System :: OS Independent
Requires-Python: >=3.8
License-File: LICENSE
Requires-Dist: python-dotenv
